{
    "Control": {
        "bass": 8.2,
        "delay_feedback": 0,
        "delay_level": 0,
        "delay_switch": 1,
        "delay_time": 512,
        "delay_type": 0,
        "fx_focus": 2,
        "gain": 9,
        "isf": 1.7,
        "master_volume": 0,
        "middle": 7.1,
        "mod_level": 3.9,
        "mod_manual": 5,
        "mod_segval": 10,
        "mod_speed": 3.9,
        "mod_switch": 0,
        "mod_type": 0,
        "presence": 9,
        "resonance": 10,
        "reverb_level": 3.9,
        "reverb_size": 10,
        "reverb_switch": 0,
        "reverb_type": 0,
        "treble": 5.4,
        "tvp_switch": 1,
        "tvp_valve": 4,
        "voice": 5,
        "volume": 4.6
    },
    "name": "default"
}